report_generators/__init__.py
report_generators/base_generator.py
report_generators/csv/__init__.py
report_generators/csv/generator.py
report_generators/pdf/Inter-Bold.ttf
report_generators/pdf/Inter-Regular.ttf
report_generators/pdf/__init__.py
report_generators/pdf/generator.py
report_generators/utils/__init__.py
report_generators/utils/text.py
report_generators/utils/types.py
report_generators/utils/workbook_to_csv.py
report_generators/xlsx/__init__.py
report_generators/xlsx/generator.py
report_generators-0.1.4.dist-info/METADATA
report_generators-0.1.4.dist-info/WHEEL
report_generators-0.1.4.dist-info/top_level.txt
report_generators-0.1.4.dist-info/RECORD
