Metadata-Version: 2.4
Name: report_generators
Version: 0.1.4
Summary: A python package for reports generation.
Home-page: https://github.com/antonoiMarchese/my_package
Author: Antônio Marchese
Author-email: Antônio Marchese <devmarcheseantonio@gmail.com>
License: MIT
Classifier: Programming Language :: Python :: 3
Classifier: License :: OSI Approved :: MIT License
Classifier: Operating System :: OS Independent
Requires-Python: >=3.6
Dynamic: author
Dynamic: home-page
Dynamic: requires-python
